rria_api/__init__.py
rria_api/abstract_robot/__init__.py
rria_api/abstract_robot/action_robot.py
rria_api/abstract_robot/connect_robot.py
rria_api/dummy/__init__.py
rria_api/dummy/action_dummy.py
rria_api/dummy/connect_dummy.py
rria_api/gen3/__init__.py
rria_api/gen3/action_gen3.py
rria_api/gen3/api_gen3/device_connection.py
rria_api/gen3/api_gen3/gen3_api.py
rria_api/gen3/connect_gen3.py
rria_api/ned/__init__.py
rria_api/ned/action_ned.py
rria_api/ned/connect_ned.py
rria_api/robot_enum.py
rria_api/robot_object.py
rria_api-1.1.1.dist-info/METADATA
rria_api-1.1.1.dist-info/WHEEL
rria_api-1.1.1.dist-info/RECORD
