Metadata-Version: 2.1
Name: rria-api
Version: 1.1.1
Summary: A package to control the Niryo Ned and the Kinova Gen3 Lite robot arms
Author: felipeadsm
Author-email: 97059009+felipeadsm@users.noreply.github.com
Requires-Python: >=3.9,<4.0
Classifier: Programming Language :: Python :: 3
Classifier: Programming Language :: Python :: 3.9
Classifier: Programming Language :: Python :: 3.10
Classifier: Programming Language :: Python :: 3.11
Classifier: Programming Language :: Python :: 3.12
Requires-Dist: pyniryo
